{
  "horarios": [
    {
      "id": "1",
      "dia": "23-05-2024",
      "horario_inicial": "07:00",
      "horario_final": "08:00",
       "cliente": "Daniel"
    },
    {
      "id": "2",
      "dia": "23-05-2024",
      "horario_inicial": "08:00",
      "horario_final": "09:00",
      "cliente": "Joaquim"
    },
    {
      "id": "3",
      "dia": "24-05-2024",
      "horario_inicial": "07:00",
      "horario_final": "08:00",
      "cliente": "Daniel"
    },
    {
      "id": "4",
      "dia": "24-05-2024",
      "horario_inicial": "08:00",
      "horario_final": "09:00",
      "cliente": "João"
    },
    {
      "id": "5",
      "dia": "25-05-2024",
      "horario_inicial": "10:00",
      "horario_final": "11:00",
      "cliente": "João"
    }
  ]
}