{
  "empresas": [
    {
      "cnpj": "12345",
      "nome": "Sol e Neve"
    }
  ],
  "user": [
    {
      "token": "151515",
      "empresa": "Sol e Neve",
      "nome": "Daniel",
      "email": "danielpimentel@gmail.com",
      "password": "senha123"
    },
    {
      "id": "42c3",
      "token": 1715108938826,
      "companyName": "Sol e Neve",
      "name": "Joaquim",
      "email": "joaquim@email.com",
      "password": "senha123"
    },
    {
      "id": "5b9e",
      "email": "joaquim@email.com",
      "password": "senha123"
    },
    {
      "id": "486c",
      "email": "fjnsjfsnfj/@email.com",
      "password": "eufhufh"
    },
    {
      "id": "55e3",
      "token": 1715109111865,
      "companyName": "Sol e Neve",
      "name": "Daniel",
      "email": "danielpimentelc5@gmail.com",
      "password": "nifnidfndfjdifjdgid"
    },
    {
      "id": "4bf0",
      "token": 1715109146058,
      "companyName": "Sol e Neve",
      "name": "Joaquim",
      "email": "joaquim@email.com",
      "password": "sfsfsfsfsf"
    },
    {
      "id": "1ab0",
      "email": "isnfisnfif@email.com",
      "password": "soifoudihdhg"
    },
    {
      "id": "bf04",
      "email": "",
      "password": ""
    }
  ]
}